tests/__init__.py
tests/conftest.py
tests/astronomical/__init__.py
tests/astronomical/test_astronomical_manager.py
tests/cruise/__init__.py
tests/cruise/test_cruise_manager.py
tests/geospatial/__init__.py
tests/geospatial/test_geospatial_manager.py
tests/record/test_echoview_record_manager.py
water_column_sonar_annotation/__init__.py
water_column_sonar_annotation/astronomical/__init__.py
water_column_sonar_annotation/astronomical/astronomical_manager.py
water_column_sonar_annotation/cruise/__init__.py
water_column_sonar_annotation/cruise/cruise_manager.py
water_column_sonar_annotation/geospatial/__init__.py
water_column_sonar_annotation/geospatial/geospatial_manager.py
water_column_sonar_annotation/record/__init__.py
water_column_sonar_annotation/record/echoview_record_manager.py
water_column_sonar_annotation/record/graph_record_manager.py
water_column_sonar_annotation/record/parquet_record_manager.py
water_column_sonar_annotation/shape/__init__.py
water_column_sonar_annotation/shape/shape_manager.py
water_column_sonar_annotation-26.1.8.dist-info/licenses/LICENSE
water_column_sonar_annotation-26.1.8.dist-info/METADATA
water_column_sonar_annotation-26.1.8.dist-info/WHEEL
water_column_sonar_annotation-26.1.8.dist-info/top_level.txt
water_column_sonar_annotation-26.1.8.dist-info/RECORD
