Metadata-Version: 2.4
Name: water-column-sonar-annotation
Version: 26.1.8
Summary: Processing Tool for Working with Water Column Sonar Annotations
Author-email: Rudy Klucik <rudy.klucik@noaa.gov>
Maintainer-email: Rudy Klucik <rudy.klucik@noaa.gov>
License-Expression: MIT
Project-URL: Homepage, https://echo.fish
Project-URL: Repository, https://github.com/CI-CMG/water-column-sonar-annotation
Project-URL: Documentation, https://github.com/CI-CMG/water-column-sonar-annotation
Project-URL: Issues, https://github.com/CI-CMG/water-column-sonar-annotation/issues
Keywords: ocean,sonar,water column
Requires-Python: >=3.12
License-File: LICENSE
Requires-Dist: build
Requires-Dist: fiona
Requires-Dist: folium
Requires-Dist: geopandas
Requires-Dist: netcdf4
Requires-Dist: numpy
Requires-Dist: pandas
Requires-Dist: pandas-stubs
Requires-Dist: pooch
Requires-Dist: pvlib
Requires-Dist: pyarrow
Requires-Dist: pyogrio
Requires-Dist: python-dotenv
Requires-Dist: s3fs
Requires-Dist: scipy
Requires-Dist: shapely
Requires-Dist: setuptools
Requires-Dist: timezonefinder
Requires-Dist: xarray
Requires-Dist: zarr
Dynamic: license-file
